COPYING
NEWS.md
README.md
bin/__init__.py
bin/main.py
conf.py
pyhids/__init__.py
pyhids/genBase.py
pyhids/genKeys.py
pyhids/hashlookup.py
pyhids/misp.py
pyhids/pandora.py
pyhids/pyHIDS.py
pyhids/utils.py
pyhids/yara_ext.py
pyhids-0.9.5.dist-info/COPYING
pyhids-0.9.5.dist-info/METADATA
pyhids-0.9.5.dist-info/WHEEL
pyhids-0.9.5.dist-info/entry_points.txt
pyhids-0.9.5.dist-info/RECORD
