Metadata-Version: 2.1
Name: pyHIDS
Version: 0.9.5
Summary: A host-based intrusion detection system.
Home-page: https://github.com/cedricbonhomme/pyHIDS
License: GPL-3.0-or-later
Keywords: hids,security,hashlookup,integrity
Author: Cédric Bonhomme
Author-email: cedric@cedricbonhomme.org
Requires-Python: >=3.11,<4.0
Classifier: Development Status :: 5 - Production/Stable
Classifier: Environment :: Console
Classifier: Intended Audience :: Developers
Classifier: Intended Audience :: Science/Research
Classifier: License :: OSI Approved :: GNU General Public License v3 or later (GPLv3+)
Classifier: Operating System :: POSIX :: Linux
Classifier: Programming Language :: Python :: 3
Classifier: Programming Language :: Python :: 3.11
Classifier: Programming Language :: Python :: 3.12
Classifier: Programming Language :: Python :: 3.10
Classifier: Topic :: Security
Requires-Dist: flor (>=1.1.3,<2.0.0)
Requires-Dist: pyhashlookup (>=1.2.1,<2.0.0)
Requires-Dist: pymisp (>=2.4.176,<3.0.0)
Requires-Dist: pypandora (>=1.5.0,<2.0.0)
Requires-Dist: rsa (>=4.9,<5.0)
Requires-Dist: scalable-cuckoo-filter (>=1.1,<2.0)
Requires-Dist: yara-python (>=4.3.1,<5.0.0)
Project-URL: Changes, https://github.com/cedricbonhomme/pyHIDS/blob/master/NEWS.md
Project-URL: Repository, https://github.com/cedricbonhomme/pyHIDS
